odoo10_addon_l10n_be_mis_reports-10.0.1.0.1-py2.7-nspkg.pth
odoo/addons/l10n_be_mis_reports/README.rst
odoo/addons/l10n_be_mis_reports/__init__.py
odoo/addons/l10n_be_mis_reports/__manifest__.py
odoo/addons/l10n_be_mis_reports/data/mis_report_bs.xml
odoo/addons/l10n_be_mis_reports/data/mis_report_pl.xml
odoo/addons/l10n_be_mis_reports/data/mis_report_styles.xml
odoo/addons/l10n_be_mis_reports/i18n/fr.po
odoo/addons/l10n_be_mis_reports/i18n/nl.po
odoo10_addon_l10n_be_mis_reports-10.0.1.0.1.dist-info/DESCRIPTION.rst
odoo10_addon_l10n_be_mis_reports-10.0.1.0.1.dist-info/METADATA
odoo10_addon_l10n_be_mis_reports-10.0.1.0.1.dist-info/RECORD
odoo10_addon_l10n_be_mis_reports-10.0.1.0.1.dist-info/WHEEL
odoo10_addon_l10n_be_mis_reports-10.0.1.0.1.dist-info/metadata.json
odoo10_addon_l10n_be_mis_reports-10.0.1.0.1.dist-info/namespace_packages.txt
odoo10_addon_l10n_be_mis_reports-10.0.1.0.1.dist-info/top_level.txt
